[
  {
    "versionCode": 3,
    "versionName": "1.0.3",
    "changes": [
      "New: Compact inline 'Go to Chapter' input inside the Table of Contents.",
      "Fixed issue where the Table of Contents scrubber could become stuck at the top.",
      "Fixed issue where some chapters would appear blank or truncated.",
      "Improved XML parsing for EPUBs with non-standard HTML entities.",
      "Enhanced reader stability with content-stable IDs for chapter elements.",
      "Added support for common text formatting tags (<br>, <hr>).",
      "Better handling of SVG-wrapped images in chapters.",
      "Improved Scrubber accuracy for shorter chapters.",
      "Enhanced TOC navigation accessibility with wider touch targets.",
      "Auto-dismiss controls when navigating via TOC or Scrubber.",
      "Reworked UI element for Table of Contents"
    ]
  },
  {
    "versionCode": 2,
    "versionName": "1.0.2",
    "changes": [
      "Added Welcome screen for fresh installs.",
      "Implemented Chapter Navigation (Previous/Next) in reader controls.",
      "Added scroll progress slider with percentage indicator.",
      "Added version tracking and automatic changelog display.",
      "Added Force LTR support for RTL languages.",
      "Improved update logic for seamless transitions.",
      "Enhanced TOC with header icons: Go to Chapter, Flipped Sort, and Locate Current.",
      "Added Ascending/Descending chapter sorting that preserves list position."
    ]
  },
  {
    "versionCode": 1,
    "versionName": "1.0.1",
    "changes": [
      "Initial release of Blue Waves EPUB Reader.",
      "Support for vertical scrolling and position restoration.",
      "Customizable themes and fonts."
    ]
  }
]